scripts/__init__.py
scripts/alien.py
scripts/alien_invasion.py
scripts/bullet.py
scripts/button.py
scripts/game_functions.py
scripts/game_stats.py
scripts/scoreboard.py
scripts/settings.py
scripts/ship.py
scripts/star.py
scripts/test_game.py
sideways_shooter/__init__.py
sideways_shooter/sideways_shooter.py
sideways_shooter/ss_bullet.py
sideways_shooter/ss_button.py
sideways_shooter/ss_game_functions.py
sideways_shooter/ss_settings.py
sideways_shooter/ss_ship.py
sideways_shooter/ss_stats.py
sideways_shooter/ss_target.py
AlienInvasion_Raph692-0.1.0.dist-info/LICENSE
AlienInvasion_Raph692-0.1.0.dist-info/METADATA
AlienInvasion_Raph692-0.1.0.dist-info/WHEEL
AlienInvasion_Raph692-0.1.0.dist-info/top_level.txt
AlienInvasion_Raph692-0.1.0.dist-info/RECORD
