Metadata-Version: 2.1
Name: AlienInvasion-Raph692
Version: 0.1.0
Summary: This package contains all scripts to run the game Alien Invasion.
Home-page: https://github.com/Raph692/Alien_Invasion
Author: Raphael
Author-email: r_bidinger@web.com
License: MIT License
Platform: UNKNOWN
Requires-Dist: pygame
